p4util/__init__.py
p4util/jnlparse.py
p4util/jnlstats.py
p4util/p4cli.py
p4util/sh.py
p4util/skel.py
p4util/test_p4cli.py
p4util/adm/__init__.py
p4util/adm/adduser2groups.py
p4util/adm/audit2db.py
p4util/adm/deluser.py
p4util/adm/jobxfr.py
p4util/adm/lsgroup.py
p4util/adm/moduser.py
p4util/adm/rm_empty_cl.py
p4util/adm/rmjobs.py
p4util/adm/sshkeys.py
p4util/helper/__init__.py
p4util/log/__init__.py
p4util/log/audit_atime.py
p4util/log/filter.py
p4util/script/__init__.py
p4util/script/backup.py
p4util/script/BranchedJobs.py
p4util/script/changes_month_depot.py
p4util/script/ClientChecker.py
p4util/script/ConfigGenerator.py
p4util/script/CountUsers.py
p4util/script/create_replica.py
p4util/script/directory_sizes.py
p4util/script/exchangeTest.py
p4util/script/hash_database.py
p4util/script/open_view_clients.py
p4util/script/P4PyReview.py
p4util/script/P4Submit.py
p4util/script/P4Sync.py
p4util/script/PerforceExchange.py
p4util/script/PerforceTransfer.py
p4util/script/PrintZip.py
p4util/script/remove_replica.py
p4util/script/SplitVerify.py
p4util/script/ThreadP4.py
p4util/script/transferTest.py
p4util/support/__init__.py
p4util/support/clients_atime.py
p4util/trigger/__init__.py
p4util/trigger/AD_auth.py
p4util/trigger/AutoArchiveTrigger.py
p4util/trigger/AutoReloadLabel.py
p4util/trigger/BuildClient.py
p4util/trigger/ChangeTypeCheckTrigger.py
p4util/trigger/CheckCaseTrigger.py
p4util/trigger/client_open_view_trigger.py
p4util/trigger/clienttrigger.py
p4util/trigger/DefaultDepotMap.py
p4util/trigger/DeleteBuildWorkspace.py
p4util/trigger/P4Triggers.py
p4util/trigger/PathLengthTrigger.py
p4util/trigger/RevisionPurger.py
p4util/user/__init__.py
p4util/user/opened_files_deleted_at_head.py
p4util/user/populate_with_move.py
p4util-0.0.1.dist-info/DESCRIPTION.rst
p4util-0.0.1.dist-info/METADATA
p4util-0.0.1.dist-info/metadata.json
p4util-0.0.1.dist-info/RECORD
p4util-0.0.1.dist-info/top_level.txt
p4util-0.0.1.dist-info/WHEEL
