Metadata-Version: 2.0
Name: p4util
Version: 0.0.1
Summary: A Toolbox for Perforce
Home-page: http://swarm.public.perforce.com/files/guest/lester_cheung/p4util
Author: Lester Cheung
Author-email: 13z73rch3un9@gmail.com
License: MIT
Keywords: p4 perforce tools scripts
Platform: UNKNOWN
Classifier: Development Status :: 3 - Alpha
Classifier: Intended Audience :: Developers
Classifier: Topic :: Software Development :: Build Tools
Classifier: License :: OSI Approved :: MIT License
Classifier: Programming Language :: Python :: 2
Classifier: Programming Language :: Python :: 2.7
Classifier: Programming Language :: Python :: 3
Classifier: Programming Language :: Python :: 3.3
